PygmentsVexLexer/__init__.py
PygmentsVexLexer/syntax/VexConstants.txt
PygmentsVexLexer/syntax/VexContexts.txt
PygmentsVexLexer/syntax/VexFunctions.txt
PygmentsVexLexer/syntax/VexKeywords.txt
PygmentsVexLexer/syntax/VexOperators.txt
PygmentsVexLexer/syntax/VexPredefined.txt
PygmentsVexLexer/syntax/VexPreprocessor.txt
PygmentsVexLexer/syntax/VexTypes.txt
PygmentsVexLexer/syntax/VexWrangleBindTypes.txt
pygmentsvexlexer-1.0.2.dist-info/entry_points.txt
pygmentsvexlexer-1.0.2.dist-info/licenses/LICENSE
pygmentsvexlexer-1.0.2.dist-info/WHEEL
pygmentsvexlexer-1.0.2.dist-info/METADATA
pygmentsvexlexer-1.0.2.dist-info/RECORD
