Metadata-Version: 2.4
Name: PygmentsVexLexer
Version: 1.0.2
Summary: Pygments Lexer for Side Effects Software's Vex and Vex Wrangle source code.
Author-email: Shawn Lipowski <vfxcodeblog@gmail.com>
License-Expression: MIT
License-File: LICENSE
Requires-Dist: pygments
Project-URL: Home, https://github.com/WhileRomeBurns/pygments-vex-lexer
